autogluon-1.4.0-py3.9-nspkg.pth
autogluon/_internal_/__init__.py
autogluon-1.4.0.dist-info/LICENSE
autogluon-1.4.0.dist-info/METADATA
autogluon-1.4.0.dist-info/NOTICE
autogluon-1.4.0.dist-info/WHEEL
autogluon-1.4.0.dist-info/namespace_packages.txt
autogluon-1.4.0.dist-info/top_level.txt
autogluon-1.4.0.dist-info/zip-safe
autogluon-1.4.0.dist-info/RECORD
